AutoDiff/__init__.py
AutoDiff/autodiff.py
AutoDiff/gradient_descent.py
AutoDiff/root_finding.py
AutoDiff_CS207_24-0.2.dist-info/LICENSE.md
AutoDiff_CS207_24-0.2.dist-info/METADATA
AutoDiff_CS207_24-0.2.dist-info/WHEEL
AutoDiff_CS207_24-0.2.dist-info/top_level.txt
AutoDiff_CS207_24-0.2.dist-info/RECORD
