Metadata-Version: 2.1
Name: AutoDiff-CS207-24
Version: 0.2
Summary: Auto Differentiation package developed for CS-207 [2019]
Home-page: https://github.com/we-the-diff/cs207-FinalProject
Author: Group 24
License: MIT
Platform: UNKNOWN
Requires-Python: >=3.6
Requires-Dist: numpy
